jpdoe/__init__.py
jpdoe/factorial.py
jpdoe-0.1.0.dist-info/licenses/LICENSE.txt
jpdoe-0.1.0.dist-info/METADATA
jpdoe-0.1.0.dist-info/WHEEL
jpdoe-0.1.0.dist-info/top_level.txt
jpdoe-0.1.0.dist-info/RECORD
