Metadata-Version: 2.4
Name: jpdoe
Version: 0.1.0
Summary: Simple design of experiment module
Author-email: John-Paul Huver <huverjohnpaul@gmail.com>
License: MIT
Project-URL: Homepage, https://github.com/HuverJohnPaul/jpdoe
Requires-Python: >=3.7
License-File: LICENSE.txt
Dynamic: license-file
